RedExtractor/__init__.py
RedExtractor/core/__init__.py
RedExtractor/core/download_helper.py
RedExtractor/core/media_object_class.py
RedExtractor/download_strategies/__init__.py
RedExtractor/download_strategies/basic_download.py
RedExtractor/download_strategies/downloading_strategy.py
RedExtractor/download_strategies/internal_parallel_download.py
RedExtractor/download_strategies/mp3_format_download.py
RedExtractor/event_driven_downloader/__init__.py
RedExtractor/event_driven_downloader/download_enqueuer.py
RedExtractor/event_driven_downloader/download_manager.py
RedExtractor/event_driven_downloader/download_worker.py
RedExtractor/progress_tracking/__init__.py
RedExtractor/progress_tracking/progress_tracking.py
RedExtractor/utils/__init__.py
RedExtractor/utils/logger.py
RedExtractor/utils/media_files_bank.py
RedExtractor/utils/url_validation.py
redextractor-0.2.2.dist-info/METADATA
redextractor-0.2.2.dist-info/WHEEL
redextractor-0.2.2.dist-info/RECORD
