Metadata-Version: 2.4
Name: RedExtractor
Version: 0.2.2
Summary: A flexible and fast multi-platform media downloading system.
Author-email: Flames Destroy <flamesdestroy913@gmail.com>
License: MIT
Requires-Python: >=3.8
Requires-Dist: pulsebus
Requires-Dist: requests
Requires-Dist: tqdm
Requires-Dist: yt-dlp
